confluence_markdown_exporter/__init__.py
confluence_markdown_exporter/api_clients.py
confluence_markdown_exporter/confluence.py
confluence_markdown_exporter/main.py
confluence_markdown_exporter/utils/__init__.py
confluence_markdown_exporter/utils/app_data_store.py
confluence_markdown_exporter/utils/config_interactive.py
confluence_markdown_exporter/utils/drawio_converter.py
confluence_markdown_exporter/utils/export.py
confluence_markdown_exporter/utils/measure_time.py
confluence_markdown_exporter/utils/platform_compat.py
confluence_markdown_exporter/utils/table_converter.py
confluence_markdown_exporter/utils/type_converter.py
confluence_markdown_exporter-3.2.0.dist-info/METADATA
confluence_markdown_exporter-3.2.0.dist-info/WHEEL
confluence_markdown_exporter-3.2.0.dist-info/entry_points.txt
confluence_markdown_exporter-3.2.0.dist-info/licenses/LICENSE
confluence_markdown_exporter-3.2.0.dist-info/RECORD
