Metadata-Version: 2.4
Name: confluence-markdown-exporter
Version: 3.2.0
Summary: A tool to export Confluence pages to Markdown
Project-URL: Homepage, https://github.com/Spenhouet/confluence-markdown-exporter
Project-URL: Documentation, https://github.com/Spenhouet/confluence-markdown-exporter/blob/main/README.md
Project-URL: Source, https://github.com/Spenhouet/confluence-markdown-exporter
Project-URL: Tracker, https://github.com/Spenhouet/confluence-markdown-exporter/issues
Author: Sebastian Penhouet
License: MIT
License-File: LICENSE
Keywords: atlassian,confluence,convertion,download,export,markdown
Requires-Python: >=3.10
Requires-Dist: atlassian-python-api
Requires-Dist: jmespath
Requires-Dist: lxml>=6.0.2
Requires-Dist: markdownify
Requires-Dist: pydantic-settings
Requires-Dist: python-dateutil
Requires-Dist: pyyaml
Requires-Dist: questionary
Requires-Dist: tabulate
Requires-Dist: tqdm
Requires-Dist: typer
